dazu/__init__.py
dazu/__main__.py
dazu/config.py
dazu/constants.py
dazu/registry.py
dazu/server.py
dazu/util.py
dazu/version.py
dazu/adapters/__init__.py
dazu/adapters/adapter.py
dazu/adapters/adapters/__init__.py
dazu/adapters/adapters/google.py
dazu/cli/__init__.py
dazu/cli/run.py
dazu/cli/train.py
dazu/cli/arguments/__init__.py
dazu/cli/arguments/run.py
dazu/cli/arguments/util.py
dazu/components/__init__.py
dazu/components/component.py
dazu/components/engine.py
dazu/components/dialogue/__init__.py
dazu/components/dialogue/simple.py
dazu/components/nlu/__init__.py
dazu/components/nlu/simple.py
dazu/routes/__init__.py
dazu/routes/api/__init__.py
dazu/routes/api/v1/__init__.py
dazu/routes/api/v1/dialog/__init__.py
dazu/training_data/__init__.py
dazu/training_data/reader.py
dazu/training_data/formats/__init__.py
dazu/training_data/formats/json.py
dazu/typing/__init__.py
dazu/typing/message.py
dazu/typing/model.py
dazu/typing/module.py
dazu/typing/training_data.py
dazu/utils/__init__.py
dazu/utils/io.py
tests/adapters/__init__.py
tests/adapters/adapter_test.py
tests/cli/__init__.py
tests/components/__init__.py
tests/typing/__init__.py
dazu-0.1.0.dist-info/LICENSE
dazu-0.1.0.dist-info/METADATA
dazu-0.1.0.dist-info/WHEEL
dazu-0.1.0.dist-info/entry_points.txt
dazu-0.1.0.dist-info/top_level.txt
dazu-0.1.0.dist-info/RECORD
