Metadata-Version: 2.1
Name: dazu
Version: 0.1.0
Summary: An engine for chatbots. Inspired by Watson Assistant and Rasa.
Home-page: https://github.com/ralphg6/dazu
Author: Raphael Pinto
Author-email: raphaelcpinto@gmail.com
Maintainer: Raphael Pinto
Maintainer-email: raphaelcpinto@gmail.com
License: Apache 2.0
Download-URL: https://github.com/ralphg6/dazu/archive/0.1.0.tar.gz
Project-URL: Bug Reports, https://github.com/ralphg6/dazu/issues
Project-URL: Source, https://github.com/ralphg6/dazu
Keywords: nlp machine-learning machine-learning-library bot bots botkit rasa conversational-agents conversational-ai chatbotchatbot-framework bot-framework watson nlu
Platform: UNKNOWN
Classifier: Development Status :: 2 - Pre-Alpha
Classifier: Intended Audience :: Developers
Classifier: License :: OSI Approved :: Apache Software License
Classifier: Programming Language :: Python
Classifier: Programming Language :: Python :: 3.6
Classifier: Programming Language :: Python :: 3.7
Classifier: Topic :: Software Development :: Libraries
Requires-Python: >=3.6
Requires-Dist: sanic (>=19.12.2)
Requires-Dist: sanic-openapi (>=0.6.1)
Requires-Dist: python-Levenshtein (==0.12.0)
Requires-Dist: Unidecode (==1.0.22)
Requires-Dist: ruamel.yaml (==0.15.94)
Requires-Dist: argparse (>=1.4.0)
